katcbf_vlbi_resample/__init__.py
katcbf_vlbi_resample/cupy_bridge.py
katcbf_vlbi_resample/hdf5_reader.py
katcbf_vlbi_resample/mk.py
katcbf_vlbi_resample/parameters.py
katcbf_vlbi_resample/polarisation.py
katcbf_vlbi_resample/power.py
katcbf_vlbi_resample/py.typed
katcbf_vlbi_resample/rechunk.py
katcbf_vlbi_resample/resample.py
katcbf_vlbi_resample/stream.py
katcbf_vlbi_resample/utils.py
katcbf_vlbi_resample/vdif_writer.py
katcbf_vlbi_resample/xrsig.py
katcbf_vlbi_resample-0.2.dist-info/licenses/LICENSE
katcbf_vlbi_resample-0.2.dist-info/METADATA
katcbf_vlbi_resample-0.2.dist-info/WHEEL
katcbf_vlbi_resample-0.2.dist-info/entry_points.txt
katcbf_vlbi_resample-0.2.dist-info/top_level.txt
katcbf_vlbi_resample-0.2.dist-info/RECORD
