Metadata-Version: 2.4
Name: katcbf_vlbi_resample
Version: 0.2
Summary: Proof-of-concept of resampling tied-array-channelised-voltages for VLBI
License-Expression: BSD-3-Clause
Project-URL: Homepage, https://github.com/ska-sa/katcbf-vlbi-resample
Project-URL: Documentation, https://katcbf-vlbi-resample.readthedocs.io
Requires-Python: >=3.12
License-File: LICENSE
Requires-Dist: astropy
Requires-Dist: atomicwrites
Requires-Dist: baseband
Requires-Dist: h5py
Requires-Dist: katsdptelstate[rdb]
Requires-Dist: numpy
Requires-Dist: packaging
Requires-Dist: platformdirs
Requires-Dist: rich
Requires-Dist: scipy
Requires-Dist: xarray
Provides-Extra: dev
Requires-Dist: build; extra == "dev"
Requires-Dist: pre-commit; extra == "dev"
Requires-Dist: pytest; extra == "dev"
Requires-Dist: pytest-asyncio; extra == "dev"
Requires-Dist: pytest-cov; extra == "dev"
Requires-Dist: pytest-custom-exit-code; extra == "dev"
Provides-Extra: doc
Requires-Dist: sphinx; extra == "doc"
Requires-Dist: sphinx-rtd-theme; extra == "doc"
Provides-Extra: cuda12x
Requires-Dist: cupy-cuda12x; extra == "cuda12x"
Dynamic: license-file
